{
  "title": "Sigmascape V2.0 (Savage)",
  "author": "Renji Sukai",
  "enrage": 630,
  "timelineData": [
    { "time": "1", "title": "--Start--", "desc": "" },
    { "time": "18", "title": "AOE + TB combo", "desc": "Tank Buster" },
    { "time": "48", "title": "Possession #1", "desc": "" },
    { "time": "65", "title": "Flash Gale", "desc": "" },
    { "time": "70", "title": "AOE + TB combo", "desc": "Tank Buster" },
    { "time": "94", "title": "Reaper tether", "desc": "" },
    { "time": "98", "title": "Demonic Howl", "desc": "Raidwide AoE" },
    { "time": "98", "title": "Divine Lure", "desc": "Lookaway" },
    { "time": "103", "title": "Demonic Pain", "desc": "" },
    { "time": "119", "title": "Demonic Howl", "desc": "Raidwide AoE" },
    { "time": "128", "title": "Release #1", "desc": "" },
    { "time": "134", "title": "Possession #2", "desc": "" },
    { "time": "162", "title": "Double AOE", "desc": "Raidwide AoE" },
    { "time": "180", "title": "First Kiss", "desc": "" },
    { "time": "195", "title": "Last Kiss", "desc": "" },
    { "time": "195", "title": "AOE + TB combo", "desc": "Tank Buster" },
    { "time": "207", "title": "Reaper tether", "desc": "" },
    { "time": "210", "title": "Divine Lure", "desc": "Lookaway" },
    { "time": "211", "title": "Demonic Storm", "desc": "" },
    { "time": "222", "title": "Demonic Howl", "desc": "Raidwide AoE" },
    { "time": "235", "title": "Release #2", "desc": "" },
    { "time": "243", "title": "Possession #3", "desc": "" },
    { "time": "266", "title": "Materialize", "desc": "" },
    { "time": "276", "title": "Demonic Pain", "desc": "" },
    { "time": "283", "title": "Lullaby", "desc": "" },
    { "time": "293", "title": "Double AOE + TB", "desc": "Tank Buster" },
    { "time": "312", "title": "Diglett chase", "desc": "" },
    { "time": "332", "title": "Demonic Howl", "desc": "Raidwide AoE" },
    { "time": "350", "title": "Release #3", "desc": "" },
    { "time": "356", "title": "Possession #4", "desc": "" },
    { "time": "383", "title": "Demonic Howl", "desc": "Raidwide AoE" },
    { "time": "393", "title": "Materialize", "desc": "" },
    { "time": "402", "title": "Mini Bait and Stack", "desc": "Stack AoE" },
    { "time": "424", "title": "Demonic Howl", "desc": "Raidwide AoE" },
    { "time": "434", "title": "Demonic Pain", "desc": "" },
    { "time": "441", "title": "First Kiss", "desc": "" },
    { "time": "446", "title": "Tsunami", "desc": "" },
    { "time": "454", "title": "AOE + TB combo", "desc": "Tank Buster" },
    { "time": "482", "title": "Release #4", "desc": "" },
    { "time": "488", "title": "Possession #5", "desc": "" },
    { "time": "548", "title": "Flash Gale", "desc": "" },
    { "time": "511", "title": "AOE + TB combo", "desc": "Tank Buster" },
    { "time": "529", "title": "Materialize", "desc": "" },
    { "time": "537", "title": "Poltergeist", "desc": "" },
    { "time": "553", "title": "AOE + TB combo", "desc": "Tank Buster" },
    { "time": "560", "title": "Divine Lure", "desc": "Lookaway" },
    { "time": "571", "title": "Demonic Pain", "desc": "" },
    { "time": "581", "title": "Demonic Howl", "desc": "Raidwide AoE" },
    { "time": "591", "title": "Release #5", "desc": "" },
    { "time": "597", "title": "Possession #4", "desc": "" },
    { "time": "617", "title": "Enrage", "desc": "" }
  ]
}
